yunnet/__init__.py
yunnet/errors.py
yunnet/yunnet_api.py
yunnet-1.3.dist-info/METADATA
yunnet-1.3.dist-info/WHEEL
yunnet-1.3.dist-info/top_level.txt
yunnet-1.3.dist-info/RECORD
